pyHydraulics/__init__.py
pyHydraulics/solver.py
pyhydraulics-0.1.0.dist-info/licenses/LICENSE
pyhydraulics-0.1.0.dist-info/METADATA
pyhydraulics-0.1.0.dist-info/WHEEL
pyhydraulics-0.1.0.dist-info/top_level.txt
pyhydraulics-0.1.0.dist-info/RECORD
